skeddly/__init__.py
skeddly/client/__init__.py
skeddly/client/actions.py
skeddly/client/configloader.py
skeddly/client/core.py
skeddly/client/credentials.py
skeddly/models/__init__.py
skeddly/models/exceptions.py
skeddly_sdk-1.0.8.dist-info/LICENSE
skeddly_sdk-1.0.8.dist-info/METADATA
skeddly_sdk-1.0.8.dist-info/WHEEL
skeddly_sdk-1.0.8.dist-info/top_level.txt
skeddly_sdk-1.0.8.dist-info/RECORD
