Metadata-Version: 2.1
Name: skeddly-sdk
Version: 1.0.8
Summary: Skeddly SDK for Python
Home-page: https://github.com/eleven41/skeddly-sdk-python
Author: Eleven41 Software Inc.
Author-email: support@skeddly.com
License: UNKNOWN
Platform: UNKNOWN
Classifier: Programming Language :: Python :: 3
Classifier: License :: OSI Approved :: MIT License
Classifier: Operating System :: OS Independent
